json_to_check/__init__.py
json_to_check/__main__.py
json_to_check/utils.py
json_to_check_cupack-0.1.0.dist-info/METADATA
json_to_check_cupack-0.1.0.dist-info/WHEEL
json_to_check_cupack-0.1.0.dist-info/top_level.txt
json_to_check_cupack-0.1.0.dist-info/RECORD
